__init__.py
dna_kmer.py
dna_kmer-0.0.1.dist-info/LICENSE
dna_kmer-0.0.1.dist-info/METADATA
dna_kmer-0.0.1.dist-info/WHEEL
dna_kmer-0.0.1.dist-info/top_level.txt
dna_kmer-0.0.1.dist-info/RECORD
