Metadata-Version: 2.1
Name: dna_kmer
Version: 0.0.1
Summary: DNA string to k-mers
Author-email: sznistvan <szni98@gmail.com>
Project-URL: Homepage, https://github.com/sznistvan/dna_kmer
Project-URL: Bug Tracker, https://github.com/sznistvan/dna_kmer/issues
Classifier: Programming Language :: Python :: 3
Classifier: License :: OSI Approved :: MIT License
Classifier: Operating System :: OS Independent
Requires-Python: >=3.7
License-File: LICENSE
